LICENSE
README.md
examples/README.md
simplebroker/__init__.py
simplebroker/__main__.py
simplebroker/_constants.py
simplebroker/_exceptions.py
simplebroker/_runner.py
simplebroker/_sql.py
simplebroker/_timestamp.py
simplebroker/cli.py
simplebroker/commands.py
simplebroker/db.py
simplebroker/ext.py
simplebroker/helpers.py
simplebroker/py.typed
simplebroker/sbqueue.py
simplebroker/watcher.py
simplebroker-2.8.4.dist-info/METADATA
simplebroker-2.8.4.dist-info/WHEEL
simplebroker-2.8.4.dist-info/entry_points.txt
simplebroker-2.8.4.dist-info/licenses/LICENSE
simplebroker-2.8.4.dist-info/RECORD
