Metadata-Version: 2.4
Name: simplebroker
Version: 2.8.4
Summary: A lightweight message queue backed by SQLite
Project-URL: Homepage, https://github.com/VanL/simplebroker
Project-URL: Documentation, https://github.com/VanL/simplebroker#readme
Project-URL: Repository, https://github.com/VanL/simplebroker.git
Project-URL: Issues, https://github.com/VanL/simplebroker/issues
Author-email: Van Lindberg <van.lindberg@gmail.com>
License: MIT
License-File: LICENSE
Keywords: broker,cli,message-queue,queue,sqlite
Classifier: Development Status :: 5 - Production/Stable
Classifier: Environment :: Console
Classifier: Intended Audience :: Developers
Classifier: License :: OSI Approved :: MIT License
Classifier: Operating System :: OS Independent
Classifier: Programming Language :: Python :: 3
Classifier: Programming Language :: Python :: 3.10
Classifier: Programming Language :: Python :: 3.11
Classifier: Programming Language :: Python :: 3.12
Classifier: Programming Language :: Python :: 3.13
Classifier: Programming Language :: Python :: 3.14
Classifier: Topic :: Software Development :: Libraries :: Python Modules
Classifier: Topic :: System :: Distributed Computing
Classifier: Topic :: Utilities
Requires-Python: >=3.10
Provides-Extra: dev
Requires-Dist: mypy>=1.0; extra == 'dev'
Requires-Dist: pytest-cov>=4.0; extra == 'dev'
Requires-Dist: pytest-timeout>=2.4.0; extra == 'dev'
Requires-Dist: pytest-xdist>=3.0; extra == 'dev'
Requires-Dist: pytest>=7.0; extra == 'dev'
Requires-Dist: ruff>=0.1.0; extra == 'dev'
